iot_upnp-1.0.3.dist-info/METADATA
iot_upnp-1.0.3.dist-info/RECORD
iot_upnp-1.0.3.dist-info/WHEEL
iot_upnp-1.0.3.dist-info/top_level.txt
upnp/HTTP.py
upnp/Objects.py
upnp/SSDP.py
upnp/UPnP.py
upnp/__init__.py
upnp/__main__.py
upnp/test_ssdp.py
