Metadata-Version: 2.1
Name: iot-upnp
Version: 1.0.3
Summary: UPnP device annoncement library
Home-page: https://github.com/bontiv/iot-upnp
Author: Remi BONNET
Author-email: bonnet@fanaticalhelp.com
License: GPLv3
Project-URL: Tracker, https://github.com/bontiv/iot-upnp/issues
Project-URL: Documentation, https://iot-upnp.readthedocs.io/
Keywords: upnp ssdp network
Platform: UNKNOWN
Classifier: Development Status :: 3 - Alpha
Classifier: Intended Audience :: Developers
Classifier: License :: OSI Approved :: GNU General Public License v2 or later (GPLv2+)
Classifier: Programming Language :: Python :: 3
Classifier: Topic :: System :: Networking
Requires-Python: >3.0
Provides-Extra: docs
Requires-Dist: ssdp
Requires-Dist: netifaces
Provides-Extra: docs
Requires-Dist: pip (>=18.0); extra == 'docs'
Requires-Dist: pbr; extra == 'docs'
Requires-Dist: sphinx; extra == 'docs'
Requires-Dist: sphinxcontrib-fulltoc; extra == 'docs'
Requires-Dist: sphinx-rtd-theme; extra == 'docs'
